MANIFEST.in
README.md
requirements.txt
setup.cfg
setup.py
versioneer.py
botcity/plugins/cloudvision/__init__.py
botcity/plugins/cloudvision/_version.py
botcity/plugins/cloudvision/pdfhandler.py
botcity/plugins/cloudvision/plugin.py
botcity_cloudvision_plugin.egg-info/PKG-INFO
botcity_cloudvision_plugin.egg-info/SOURCES.txt
botcity_cloudvision_plugin.egg-info/dependency_links.txt
botcity_cloudvision_plugin.egg-info/requires.txt
botcity_cloudvision_plugin.egg-info/top_level.txt
tests/test_import.py
tests/test_plugin.py